apio/__init__.py
apio/__main__.py
apio/apio_context.py
apio/profile.py
apio/commands/__init__.py
apio/commands/apio.py
apio/commands/apio_api.py
apio/commands/apio_boards.py
apio/commands/apio_build.py
apio/commands/apio_clean.py
apio/commands/apio_create.py
apio/commands/apio_devices.py
apio/commands/apio_docs.py
apio/commands/apio_drivers.py
apio/commands/apio_drivers_install.py
apio/commands/apio_drivers_uninstall.py
apio/commands/apio_examples.py
apio/commands/apio_format.py
apio/commands/apio_fpgas.py
apio/commands/apio_graph.py
apio/commands/apio_info.py
apio/commands/apio_lint.py
apio/commands/apio_packages.py
apio/commands/apio_preferences.py
apio/commands/apio_raw.py
apio/commands/apio_report.py
apio/commands/apio_sim.py
apio/commands/apio_test.py
apio/commands/apio_upgrade.py
apio/commands/apio_upload.py
apio/commands/options.py
apio/common/README.md
apio/common/__init__.py
apio/common/apio_console.py
apio/common/apio_styles.py
apio/common/apio_themes.py
apio/common/common_util.py
apio/common/rich_lib_windows.py
apio/common/proto/__init__.py
apio/common/proto/apio.proto
apio/common/proto/apio_pb2.py
apio/common/proto/apio_pb2.pyi
apio/common/proto/update-protos.sh
apio/managers/__init__.py
apio/managers/downloader.py
apio/managers/drivers.py
apio/managers/examples.py
apio/managers/packages.py
apio/managers/programmers.py
apio/managers/project.py
apio/managers/scons_filter.py
apio/managers/scons_manager.py
apio/managers/unpacker.py
apio/resources/80-fpga-ftdi.rules
apio/resources/80-fpga-serial.rules
apio/resources/config.jsonc
apio/resources/packages.jsonc
apio/resources/platforms.jsonc
apio/scons/README.md
apio/scons/SConstruct
apio/scons/__init__.py
apio/scons/apio_env.py
apio/scons/plugin_base.py
apio/scons/plugin_ecp5.py
apio/scons/plugin_gowin.py
apio/scons/plugin_ice40.py
apio/scons/plugin_util.py
apio/scons/scons_handler.py
apio/utils/__init__.py
apio/utils/cmd_util.py
apio/utils/env_options.py
apio/utils/jsonc.py
apio/utils/resource_util.py
apio-1.2.1.dist-info/entry_points.txt
apio-1.2.1.dist-info/licenses/LICENSE
apio-1.2.1.dist-info/WHEEL
apio-1.2.1.dist-info/METADATA
apio-1.2.1.dist-info/RECORD
