Metadata-Version: 2.4
Name: apio
Version: 1.2.1
Summary: Open source ecosystem for open FPGA boards
Home-page: https://github.com/fpgawars/apio
Author: Jesus Arroyo
Author-email: jesus.jkhlg@gmail.com 
Requires-Python: >=3.11
Classifier: Development Status :: 5 - Production/Stable
Classifier: Environment :: Console
Classifier: Intended Audience :: Developers
Classifier: License :: OSI Approved :: GNU General Public License v2 (GPLv2)
Classifier: Programming Language :: Python
Classifier: Natural Language :: English
Classifier: Topic :: Scientific/Engineering :: Electronic Design Automation (EDA)
License-File: LICENSE
Requires-Dist: click==8.2.1
Requires-Dist: colorama==0.4.6
Requires-Dist: configobj==5.0.9
Requires-Dist: debugpy==1.8.19
Requires-Dist: packaging==25.0
Requires-Dist: pyserial==3.5
Requires-Dist: requests==2.32.4
Requires-Dist: scons==4.8.1
Requires-Dist: semantic_version==2.10.0
Requires-Dist: wheel==0.45.1
Requires-Dist: blackiceprog==2.0.0
Requires-Dist: tinyfpgab==1.1.0
Requires-Dist: tinyprog==1.0.21
Requires-Dist: icefunprog==2.0.3
Requires-Dist: apycula==0.15
Requires-Dist: apollo_fpga==1.1.1
Requires-Dist: protobuf==6.33.0
Requires-Dist: rich==14.0.0
Requires-Dist: invoke==2.2.1
Requires-Dist: blackiceprog==2.0.0 ; extra == "blackiceprog"
Requires-Dist: icefunprog==2.0.3 ; extra == "icefunprog"
Requires-Dist: litterbox==0.2.2 ; extra == "litterbox"
Requires-Dist: tinyfpgab==1.1.0 ; extra == "tinyfpgab"
Project-URL: Bugs Tracker, https://github.com/fpgawars/apio/issues
Project-URL: Discussions, https://github.com/fpgawars/apio/discussions
Project-URL: Documentation, https://fpgawars.github.io/apio/docs
Project-URL: Homepage, https://github.com/fpgawars/apio
Project-URL: Wiki, https://github.com/fpgawars/apio/wiki
Provides-Extra: blackiceprog
Provides-Extra: icefunprog
Provides-Extra: litterbox
Provides-Extra: tinyfpgab
